stripepy/__init__.py
stripepy/main.py
stripepy/plot.py
stripepy/utils.py
stripepy/algorithms/finders.py
stripepy/algorithms/regressions.py
stripepy/algorithms/step1.py
stripepy/algorithms/step2.py
stripepy/algorithms/step3.py
stripepy/algorithms/step4.py
stripepy/algorithms/step5.py
stripepy/cli/call.py
stripepy/cli/download.py
stripepy/cli/plot.py
stripepy/cli/setup.py
stripepy/cli/telemetry.py
stripepy/cli/view.py
stripepy/data_structures/__init__.py
stripepy/data_structures/concurrent.py
stripepy/data_structures/persistence1d.py
stripepy/data_structures/result.py
stripepy/data_structures/result_file.py
stripepy/data_structures/shared_sparse_matrix.py
stripepy/data_structures/stripe.py
stripepy/data_structures/unionfind.py
stripepy/io/__init__.py
stripepy/io/common.py
stripepy/io/logging.py
stripepy/io/progress_bar.py
stripepy_hic-1.2.0.dist-info/METADATA
stripepy_hic-1.2.0.dist-info/WHEEL
stripepy_hic-1.2.0.dist-info/entry_points.txt
stripepy_hic-1.2.0.dist-info/licenses/LICENCE
stripepy_hic-1.2.0.dist-info/RECORD
