Metadata-Version: 2.4
Name: stripepy-hic
Version: 1.2.0
Summary: StripePy recognizes architectural stripes in 3C and Hi-C contact maps using geometric reasoning
Project-URL: Homepage, https://github.com/paulsengroup/StripePy
Project-URL: Issues, https://github.com/paulsengroup/StripePy/issues
Project-URL: Repository, https://github.com/paulsengroup/StripePy.git
Project-URL: Source, https://github.com/paulsengroup/StripePy
Author-email: Andrea Raffo <andrea.raffo@ibv.uio.no>, Roberto Rossini <roberros@uio.no>
Maintainer-email: Andrea Raffo <andrea.raffo@ibv.uio.no>, Roberto Rossini <roberros@uio.no>
License-Expression: MIT
License-File: LICENCE
Keywords: architectural stripe,contact map,cooler,hi-c,hic,stripe,stripe recognition,stripes
Classifier: Intended Audience :: Science/Research
Classifier: Operating System :: OS Independent
Classifier: Programming Language :: Python :: 3
Classifier: Programming Language :: Python :: 3.9
Classifier: Programming Language :: Python :: 3.10
Classifier: Programming Language :: Python :: 3.11
Classifier: Programming Language :: Python :: 3.12
Classifier: Programming Language :: Python :: 3.13
Classifier: Topic :: Scientific/Engineering :: Bio-Informatics
Requires-Python: >=3.9
Requires-Dist: h5py<4,>3
Requires-Dist: hictkpy[scipy]<2,>=1.2
Requires-Dist: numpy<3,>=2
Requires-Dist: opentelemetry-api<2,>=1
Requires-Dist: opentelemetry-exporter-otlp-proto-http<2,>=1
Requires-Dist: opentelemetry-sdk<2,>=1
Requires-Dist: packaging
Requires-Dist: pandas<3,>=2.0
Requires-Dist: scipy<2,>=1.10
Requires-Dist: structlog<26,>=24
Provides-Extra: all
Requires-Dist: colorama<0.5,>=0.4; extra == 'all'
Requires-Dist: matplotlib<4,>=3.8; extra == 'all'
Requires-Dist: rich<15,>=13.9; extra == 'all'
Provides-Extra: dev
Requires-Dist: black[jupyter]; extra == 'dev'
Requires-Dist: build; extra == 'dev'
Requires-Dist: colorama<0.5,>=0.4; extra == 'dev'
Requires-Dist: furo==2024.8.6; extra == 'dev'
Requires-Dist: ipython==9.5.0; extra == 'dev'
Requires-Dist: isort; extra == 'dev'
Requires-Dist: matplotlib<4,>=3.8; extra == 'dev'
Requires-Dist: pre-commit; extra == 'dev'
Requires-Dist: pyarrow; extra == 'dev'
Requires-Dist: pytest; extra == 'dev'
Requires-Dist: pytest-cov; extra == 'dev'
Requires-Dist: rich<15,>=13.9; extra == 'dev'
Requires-Dist: sphinx-copybutton==0.5.2; extra == 'dev'
Requires-Dist: sphinx==8.2.3; extra == 'dev'
Provides-Extra: docs
Requires-Dist: furo==2024.8.6; extra == 'docs'
Requires-Dist: ipython==9.5.0; extra == 'docs'
Requires-Dist: sphinx-copybutton==0.5.2; extra == 'docs'
Requires-Dist: sphinx==8.2.3; extra == 'docs'
Provides-Extra: test
Requires-Dist: colorama<0.5,>=0.4; extra == 'test'
Requires-Dist: matplotlib<4,>=3.8; extra == 'test'
Requires-Dist: pyarrow; extra == 'test'
Requires-Dist: pytest; extra == 'test'
Requires-Dist: pytest-cov; extra == 'test'
Requires-Dist: rich<15,>=13.9; extra == 'test'
